jade/__init__.py
jade/__main__.py
jade/utilities.py
jade/app/__init__.py
jade/app/app.py
jade/app/fetch.py
jade/config/__init__.py
jade/config/atlas_config.py
jade/config/excel_config.py
jade/config/paths_tree.py
jade/config/pp_config.py
jade/config/raw_config.py
jade/config/run_config.py
jade/config/status.py
jade/config/resources/__init--.py
jade/gui/__init__.py
jade/gui/post_config_gui.py
jade/gui/run_config_gui.py
jade/helper/__init__.py
jade/helper/__optionals__.py
jade/helper/aux_functions.py
jade/helper/constants.py
jade/helper/errors.py
jade/helper/openmc.py
jade/post/__init__.py
jade/post/atlas.py
jade/post/atlas_processor.py
jade/post/excel_processor.py
jade/post/excel_routines.py
jade/post/manipulate_tally.py
jade/post/plotter.py
jade/post/raw_processor.py
jade/post/sim_output.py
jade/resources/Jade.ico
jade/resources/__init__.py
jade/resources/atlas_template.docx
jade/resources/default_cfg/__init__.py
jade/resources/default_cfg/env_vars_cfg.yml
jade/resources/default_cfg/libs_cfg.yml
jade/resources/default_cfg/pp_cfg.yml
jade/resources/default_cfg/run_cfg.yml
jade/resources/default_cfg/benchmarks/__init__.py
jade/resources/default_cfg/benchmarks/Sphere/MaterialsSettings.csv
jade/resources/default_cfg/benchmarks/Sphere/ZaidSettings.csv
jade/resources/default_cfg/benchmarks/Sphere/__init__.py
jade/resources/default_cfg/benchmarks/SphereSDDR/MaterialsSettings.csv
jade/resources/default_cfg/benchmarks/SphereSDDR/ZaidSettings.csv
jade/resources/default_cfg/benchmarks/SphereSDDR/__init__.py
jade/resources/default_cfg/benchmarks/SphereSDDR/irrad_93c.txt
jade/resources/default_cfg/benchmarks/SphereSDDR/irrad_98c.txt
jade/resources/default_cfg/benchmarks/SphereSDDR/irrad_99c.txt
jade/resources/default_cfg/benchmarks_pp/__init__.py
jade/resources/default_cfg/benchmarks_pp/atlas/ASPIS-Fe88.yaml
jade/resources/default_cfg/benchmarks_pp/atlas/ASPIS-PCA-Replica.yaml
jade/resources/default_cfg/benchmarks_pp/atlas/C-Model.yaml
jadevv-4.3.0.dist-info/licenses/LICENSE
jadevv-4.3.0.dist-info/licenses/LICENSE_PYNE
jadevv-4.3.0.dist-info/METADATA
jadevv-4.3.0.dist-info/WHEEL
jadevv-4.3.0.dist-info/top_level.txt
jadevv-4.3.0.dist-info/RECORD
