Metadata-Version: 2.4
Name: jadevv
Version: 4.3.0
Summary: JADE, a V&V tool for nuclear data libraries and transport codes
Author-email: JADE dev team <sc-radiationtransport@f4e.europa.eu>
License:                     GNU GENERAL PUBLIC LICENSE
Project-URL: Homepage, https://github.com/JADE-V-V/JADE
Project-URL: Repository, https://github.com/JADE-V-V/JADE
Project-URL: Documentation, https://jade-a-nuclear-data-libraries-vv-tool.readthedocs.io/en/latest/
Classifier: Programming Language :: Python :: 3
Classifier: License :: OSI Approved :: European Union Public Licence 1.2 (EUPL 1.2)
Classifier: Operating System :: OS Independent
Requires-Python: >=3.10
License-File: LICENSE
License-File: LICENSE_PYNE
Requires-Dist: xlsxwriter
Requires-Dist: matplotlib
Requires-Dist: aspose-words
Requires-Dist: requests
Requires-Dist: f4enix>=0.15.0
Requires-Dist: pyyaml
Requires-Dist: seaborn
Requires-Dist: python-gitlab
Provides-Extra: dev
Requires-Dist: pytest; extra == "dev"
Requires-Dist: pytest-cov; extra == "dev"
Requires-Dist: pytest-xvfb; extra == "dev"
Requires-Dist: ruff; extra == "dev"
Requires-Dist: sphinx; extra == "dev"
Requires-Dist: myst-parser; extra == "dev"
Requires-Dist: sphinx-book-theme; extra == "dev"
Requires-Dist: sphinx-copybutton; extra == "dev"
Requires-Dist: sphinx-togglebutton; extra == "dev"
Requires-Dist: sphinx-design; extra == "dev"
Provides-Extra: ui
Requires-Dist: ttkthemes; extra == "ui"
Dynamic: license-file
